sanau/__init__.py
sanau/example.py
sanau-0.0.1.dist-info/LICENSE
sanau-0.0.1.dist-info/METADATA
sanau-0.0.1.dist-info/WHEEL
sanau-0.0.1.dist-info/top_level.txt
sanau-0.0.1.dist-info/RECORD
