Metadata-Version: 2.1
Name: sanau
Version: 0.0.1
Summary: Sanau package
Home-page: https://github.com/ayazhan-sanau/sanau
Author: Ayazhan Zhakhan
Author-email: az@sanau.co
License: UNKNOWN
Platform: UNKNOWN
Classifier: Programming Language :: Python :: 3
Classifier: License :: OSI Approved :: MIT License
Classifier: Operating System :: OS Independent
Requires-Python: >=3.6
